datavistaflow/__init__.py
datavistaflow/src/__init__.py
datavistaflow/src/datavistaflow.py
datavistaflow-0.0.16.dist-info/LICENSE
datavistaflow-0.0.16.dist-info/METADATA
datavistaflow-0.0.16.dist-info/WHEEL
datavistaflow-0.0.16.dist-info/top_level.txt
datavistaflow-0.0.16.dist-info/RECORD
