Metadata-Version: 2.1
Name: datavistaflow
Version: 0.0.16
Summary: An data visualization library to generate dynamic plots
Home-page: https://github.com/spoorthiuk/datavistaflow
Author: Spoorthi U K
Author-email: spoorthiuday27@gmail.com
License: MIT
Classifier: License :: OSI Approved :: MIT License
Classifier: Programming Language :: Python :: 3
Classifier: Operating System :: OS Independent
Requires-Python: >=3.9
License-File: LICENSE
Requires-Dist: matplotlib >=3.8.0
Provides-Extra: dev
Requires-Dist: pytest >=7.0 ; extra == 'dev'
Requires-Dist: twine >=4.0.2 ; extra == 'dev'
